kasserver/KasApi.wsdl
kasserver/__init__.py
kasserver/kasserver_dns.py
kasserver/kasserver_dns_certbot.py
kasserver/kasserver_dns_lego.py
kasserver-0.4.2.dist-info/METADATA
kasserver-0.4.2.dist-info/WHEEL
kasserver-0.4.2.dist-info/entry_points.txt
kasserver-0.4.2.dist-info/licenses/LICENSE.txt
kasserver-0.4.2.dist-info/RECORD
