Metadata-Version: 2.4
Name: kasserver
Version: 0.4.2
Summary: Manage domains hosted on All-Inkl.com through the KAS server API
Project-URL: Repository, https://github.com/fetzerch/kasserver
Author-email: Christian Fetzer <fetzer.ch@gmail.com>
License-Expression: MIT
License-File: LICENSE.txt
Classifier: Development Status :: 4 - Beta
Classifier: Environment :: Console
Classifier: Intended Audience :: System Administrators
Classifier: Natural Language :: English
Classifier: Operating System :: POSIX
Classifier: Programming Language :: Python
Classifier: Topic :: System :: Systems Administration
Requires-Python: >=3.10
Requires-Dist: click>=8.2.1
Requires-Dist: zeep>=4.3.1
